{"cameraMode":{"drawMode":0,"name":"Shaded","section":"Shading Mode"},"sceneLighting":true,"audioPlay":false,"sceneViewState":{"m_AlwaysRefresh":false,"showFog":true,"showSkybox":true,"showFlares":true,"showImageEffects":true,"showParticleSystems":true,"showVisualEffectGraphs":true,"m_FxEnabled":true},"in2DMode":false,"pivot":{"x":427.91009521484377,"y":256.66326904296877,"z":-113.22286987304688},"rotation":{"x":-0.036270275712013248,"y":0.028177648782730104,"z":0.0009983795462176204,"w":0.9989826083183289},"size":73.23444366455078,"orthographic":false}